{
  "products": [
    {
      "id": 1,
      "title": "Product 1",
      "price": 10,
      "quantity": 1
    },
    {
      "id": 2,
      "title": "Hat 2",
      "price": 200,
      "quantity": 1
    },
    {
      "id": 3,
      "title": "Shirt 3",
      "price": 400,
      "quantity": 1
    },
    {
      "id": 4,
      "title": "Dress 4",
      "price": 40,
      "quantity": 1
    },
    {
      "id": 5,
      "title": "Polo 5",
      "price": 540,
      "quantity": 1
    },
    {
      "id": 6,
      "title": "Demi 6",
      "price": 60,
      "quantity": 1
    }
  ],
  "cart": {
    "cartItems": [],
    "totalPrice": 0,
    "totalProduct": 7
  },
  "users": {
    "accountItem": [
      {
        "name": "Le Xuan Truong",
        "email": "truong@gmail.com",
        "password": "123123"
      },
      {
        "name": "tung",
        "email": "tung123@gmail.com",
        "password": "123123"
      },
      {
        "name": "tung123",
        "email": "tung1234@gmail.com",
        "password": "123123"
      },
      {
        "name": "Hoa Thi",
        "email": "hoa@gmail.com",
        "password": "123123"
      },
      {
        "name": "huyen",
        "email": "huyen@gmail.com",
        "password": "123123"
      },
      {
        "name": "Tram Anh",
        "email": "tramanh@gmail.com",
        "password": "123123"
      },
      {
        "name": "Tram Anh",
        "email": "tramanh123@gmail.com",
        "password": "123123"
      },
      {
        "name": "Tram Anh",
        "email": "tramanh123456@gmail.com",
        "password": "123123"
      },
      {
        "name": "Tram Anh",
        "email": "tramanh12345678@gmail.com",
        "password": "123123"
      },
      {
        "name": "ngoc tram",
        "email": "ngoctram@gmail.com",
        "password": "123123"
      },
      {
        "name": "truong678",
        "email": "truonggg@gmail.com",
        "password": "123123"
      },
      {
        "name": "truong678",
        "email": "truonggg00@gmail.com",
        "password": "123123"
      },
      {
        "name": "truong678",
        "email": "truonggg005646@gmail.com",
        "password": "123123"
      },
      {
        "name": "truong678",
        "email": "truonggg0056463123@gmail.com",
        "password": "123123"
      },
      {
        "name": "truong678",
        "email": "truongggsa0056463123@gmail.com",
        "password": "123123"
      },
      {
        "name": "truong",
        "email": "truong00909@gmail.com",
        "password": "123123"
      },
      {
        "name": "dat",
        "email": "dat@gmail.com",
        "password": "123123"
      },
      {
        "name": "dat",
        "email": "da1212t@gmail.com",
        "password": "123123"
      },
      {
        "name": "dat312312",
        "email": "da1212tqsas@gmail.com",
        "password": "123123"
      },
      {
        "name": "dat312312",
        "email": "da1212tqsas123123@gmail.com",
        "password": "123123"
      },
      {
        "name": "tam",
        "email": "tam@gmail.com",
        "password": "123123"
      },
      {
        "name": "hoa",
        "email": "hoan@gmail.com",
        "password": "123123"
      },
      {
        "name": "hoa",
        "email": "hoa123@gmail.com",
        "password": "123123"
      },
      {
        "name": "quang",
        "email": "quang090@gmail.com",
        "password": "123123"
      },
      {
        "name": "hung",
        "email": "hung@gmail.com",
        "password": "123123"
      },
      {
        "name": "quang123",
        "email": "quang909@gmail.com",
        "password": "123123"
      },
      {
        "name": "vy ho ",
        "email": "vyho@gmail.com",
        "password": "123123"
      },
      {
        "name": "truong",
        "email": "truongasd@gmail.com",
        "password": "123123"
      },
      {
        "name": "cuong",
        "email": "cuong@gmail.com",
        "password": "123123"
      },
      {
        "name": "cuong pham",
        "email": "phamcuong@gmail.com",
        "password": "123123"
      }
    ]
  }
}